caas/__init__.py
caas/anthropic_client.py
caas/cli.py
caas/config.py
caas/gate.py
caas/memory.py
caas/pnl.py
caas/pumpportal_launcher.py
caas/pumpportal_trader.py
caas/repl.py
caas/runtime.py
caas/secrets.py
caas/session.py
caas/trade_core.py
caas/ui.py
caas/wallet_value.py
caas/winmask.py
caas_cli-1.1.1.dist-info/METADATA
caas_cli-1.1.1.dist-info/WHEEL
caas_cli-1.1.1.dist-info/entry_points.txt
caas_cli-1.1.1.dist-info/top_level.txt
caas_cli-1.1.1.dist-info/RECORD
