Metadata-Version: 2.4
Name: caas-cli
Version: 1.1.1
Summary: Companion as a Service: CLI companion + Pump.fun trading/launching.
Author: backgroundpr
License: MIT
Requires-Python: >=3.9
Requires-Dist: typer<1.0,>=0.12.3
Requires-Dist: rich>=13.7.1
Requires-Dist: prompt-toolkit>=3.0.47
Requires-Dist: keyring>=25.2.1
Requires-Dist: pydantic>=2.8.2
Requires-Dist: platformdirs>=4.2.2
Requires-Dist: requests>=2.32.3
Requires-Dist: solders>=0.21.0
Requires-Dist: base58>=2.1.1
